performer_pytorch/__init__.py
performer_pytorch/autoregressive_wrapper.py
performer_pytorch/performer_enc_dec.py
performer_pytorch/performer_pytorch.py
performer_pytorch/reversible.py
tikt_performer_pytorch-0.15.1.1.dist-info/LICENSE
tikt_performer_pytorch-0.15.1.1.dist-info/METADATA
tikt_performer_pytorch-0.15.1.1.dist-info/WHEEL
tikt_performer_pytorch-0.15.1.1.dist-info/top_level.txt
tikt_performer_pytorch-0.15.1.1.dist-info/RECORD
