Metadata-Version: 2.1
Name: tikt-performer-pytorch
Version: 0.15.1.1
Summary: Performer - Pytorch
Home-page: https://github.com/napoler/performer-pytorch
Author: Phil Wang
Author-email: lucidrains@gmail.com
License: MIT
Keywords: artificial intelligence,attention mechanism,efficient attention,transformers
Platform: UNKNOWN
Classifier: Development Status :: 4 - Beta
Classifier: Intended Audience :: Developers
Classifier: Topic :: Scientific/Engineering :: Artificial Intelligence
Classifier: License :: OSI Approved :: MIT License
Classifier: Programming Language :: Python :: 3.6
Requires-Dist: einops (>=0.3)
Requires-Dist: local-attention (>=1.1.1)
Requires-Dist: pytorch-fast-transformers (>=0.3.0)
Requires-Dist: torch (>=1.6)
Requires-Dist: axial-positional-embedding (>=0.1.0)
